Metadata-Version: 2.2
Name: flatmate
Version: 0.0.0
Summary: flatmate - Your Friendly Data Flattener. Converted Nested JSON from an API into a List of Single-Depth Dictionaries for Writing to a CSV
Home-page: https://github.com/DanielJDufour/flatmate
Download-URL: https://github.com/DanielJDufour/flatmate/tarball/download
Author: Daniel J. Dufour
Author-email: daniel.j.dufour@gmail.com
Keywords: csv,data,flat,flatten
Classifier: Programming Language :: Python :: 3
Classifier: Operating System :: OS Independent
License-File: LICENSE
Requires-Dist: sendero
Dynamic: author
Dynamic: author-email
Dynamic: classifier
Dynamic: description
Dynamic: description-content-type
Dynamic: download-url
Dynamic: home-page
Dynamic: keywords
Dynamic: requires-dist
Dynamic: summary
